scup.py
scup-0.4.5.dist-info/METADATA
scup-0.4.5.dist-info/WHEEL
scup-0.4.5.dist-info/RECORD
