Metadata-Version: 2.1
Name: scup
Version: 0.4.5
Summary: SCUP as in SQL Covertor Utility Program
Author: Akansha K
Author-email: akanshakaushik0995@gmail.com
Requires-Python: >=3.10,<4.0
Classifier: Programming Language :: Python :: 3
Classifier: Programming Language :: Python :: 3.10
Classifier: Programming Language :: Python :: 3.11
Project-URL: Bug Tracker, https://github.com/ankit48365/SCU/issues
Project-URL: Homepage, https://github.com/ankit48365/SCU
